<?xml version="1.0" encoding="utf-8" ?>
<dwsync>
<file name="food1.jpg" server="C:/wamp/www/foodshare/" local="131054533894726655" remote="131054533890000000" Dst="0" />
<file name="food2.jpg" server="C:/wamp/www/foodshare/" local="131054534049261504" remote="131054534040000000" Dst="0" />
<file name="food3.jpg" server="C:/wamp/www/foodshare/" local="131054534342612994" remote="131054534340000000" Dst="0" />
<file name="food1.jpg" server="C:/wamp/www/foodshare_2/" local="131054533894726655" remote="131054533890000000" Dst="0" />
<file name="food2.jpg" server="C:/wamp/www/foodshare_2/" local="131054534049261504" remote="131054534040000000" Dst="0" />
<file name="food3.jpg" server="C:/wamp/www/foodshare_2/" local="131054534342612994" remote="131054534340000000" Dst="0" />
<file name="warm.gif" server="C:/wamp/www/foodshare_2/" local="131056978824458888" remote="131056978820000000" Dst="0" />
<file name="warm.gif" server="C:/wamp/www/foodshare1/" local="131056978824458888" remote="131056978820000000" Dst="0" />
<file name="food1.jpg" server="C:/wamp/www/foodshare1/" local="131060754393539232" remote="131060754390000000" Dst="0" />
<file name="food2.jpg" server="C:/wamp/www/foodshare1/" local="131060754537835191" remote="131060754530000000" Dst="0" />
<file name="food3.jpg" server="C:/wamp/www/foodshare1/" local="131060754488461798" remote="131060754480000000" Dst="0" />
</dwsync>